crispr_millipede/__init__.py
crispr_millipede/encoding/__init__.py
crispr_millipede/encoding/encoding.py
crispr_millipede/encoding/visualization.py
crispr_millipede/modelling/__init__.py
crispr_millipede/modelling/defaults.py
crispr_millipede/modelling/models_inputs.py
crispr_millipede/modelling/models_processing.py
crispr_millipede/modelling/pydeseq.py
crispr_millipede/modelling/utility.py
crispr_millipede/utility/__init__.py
crispr_millipede/utility/utility.py
crispr_millipede/visualization/__init__.py
crispr_millipede/visualization/allele_visualization.py
crispr_millipede/visualization/board_plot_visualization.py
crispr_millipede/visualization/models_visualization.py
crispr_millipede-0.1.172.dist-info/LICENSE.txt
crispr_millipede-0.1.172.dist-info/METADATA
crispr_millipede-0.1.172.dist-info/WHEEL
crispr_millipede-0.1.172.dist-info/RECORD
