Metadata-Version: 2.1
Name: crispr-millipede
Version: 0.1.172
Summary: Calculate the enrichment scores of CRISPR alleles and variants from direct target amplicon-sequencing data using Bayesian linear regression model 'millipede'
Author: Basheer Becerra
Author-email: bbecerra@fas.harvard.edu
Requires-Python: >=3.10,<4.0
Classifier: Programming Language :: Python :: 3
Classifier: Programming Language :: Python :: 3.10
Classifier: Programming Language :: Python :: 3.11
Requires-Dist: biopython (>=1.81,<2.0)
Requires-Dist: crispr-shrinkage (==0.1.63)
Requires-Dist: ipywidgets (>=8.1.2,<9.0.0)
Requires-Dist: kaleido (==0.2.1)
Requires-Dist: matplotlib (>=3.8,<4.0)
Requires-Dist: millipede-regression (==0.1.7)
Requires-Dist: nbformat (>=4.2.0)
Requires-Dist: numpy (>=1.26,<2.0)
Requires-Dist: pandarallel (>=1.6.4,<2.0.0)
Requires-Dist: pandas (>=1.5,<2.0)
Requires-Dist: plotly (==5.9.0)
Requires-Dist: pydeseq2 (==0.4.4)
Requires-Dist: scipy (>=1.13,<2.0)
Requires-Dist: seaborn (==0.13.2)
Requires-Dist: typeguard (>=3.0.2,<4.0.0)
